Workbook

Sheet Variables
A1: Guía de variables del Inspector – Patrol Scrap (Unity)
A2: Leyenda: azul = valor inicial de los scripts (constante) · fondo amarillo = columna 'Mi valor', escribe aquí los tuyos. Si la dejas vacía, las fórmulas de la hoja 'Relaciones' usan el valor inicial.
A4: Script | B4: Sección | C4: Variable | D4: Valor inicial | E4: Unidad | F4: Mi valor | G4: Para qué sirve | H4: Si la subes | I4: Si la bajas
A5: SuspensionCoche | B5: Ruedas | C5: Ruedas (lista) | D5: 4 elementos | G5: Una entrada por rueda (FL, FR, BL, BR)
A6: SuspensionCoche | B6: Ruedas | C6: Anclaje | D6: Rueda_XX | G6: Punto de donde sale el SphereCast. Las delanteras giran aquí
A7: SuspensionCoche | B7: Ruedas | C7: Pivote | D7: Pivote | G7: Objeto visual que sube y baja con el resorte
A8: SuspensionCoche | B8: Ruedas | C8: Delantera | D8: Sí en FL y FR | G8: Marca las ruedas que giran con la dirección
A9: SuspensionCoche | B9: Ruedas | C9: Traccion | D9: Sí en las 4 | G9: Marca las ruedas que reciben fuerza del motor (4x4)
A10: SuspensionCoche | B10: Suspensión | C10: Capa Suelo | D10: Suelo | G10: Capa que detecta el SphereCast. Si no está marcada, el coche cae
A11: SuspensionCoche | B11: Suspensión | C11: Longitud Maxima | D11: 0.9 | E11: m | G11: Recorrido total del resorte (desde el anclaje hasta donde llega el cast) | H11: Más recorrido y más exagerado | I11: Toca fondo antes
A12: SuspensionCoche | B12: Suspensión | C12: Radio Rueda | D12: 0.5 | E12: m | G12: Radio de la esfera del cast. Debe coincidir con el neumático real | H12: Si no coincide con el neumático, la rueda se ve hundida o flotando
A13: SuspensionCoche | B13: Suspensión | C13: Rigidez | D13: 25000 | E13: N/m | G13: Fuerza del resorte por metro comprimido | H13: Coche duro | I13: Coche blando, se hunde y se balancea
A14: SuspensionCoche | B14: Suspensión | C14: Amortiguacion | D14: 2500 | E14: N·s/m | G14: Frena el rebote según la velocidad de compresión | H14: Se asienta rápido, sin vida | I14: Rebota varias veces
A15: SuspensionCoche | B15: Tope | C15: Inicio Tope | D15: 0.8 | E15: fracción (0.5-0.95) | G15: A qué fracción del recorrido empieza el 'tope de goma' | H15: El tope actúa más tarde | I15: El tope actúa antes
A16: SuspensionCoche | B16: Tope | C16: Rigidez Tope | D16: 150000 | E16: N/m | G16: Dureza extra al final del recorrido, para que el cuerpo no toque fondo | H16: Tope más duro | I16: Tope más blando
A17: SuspensionCoche | B17: Depuración | C17: Mostrar Gizmos | D17: No | G17: Dibuja esferas amarillas (recorrido) y rojas (física) en la Scene
A18: EntradaCoche | B18: Entrada | C18: Velocidad Acelerador | D18: 3 | E18: unidades/s | G18: Lo rápido que sube el acelerador de 0 a 1 | H18: Respuesta brusca | I18: Más progresiva
A19: EntradaCoche | B19: Entrada | C19: Velocidad Direccion | D19: 4 | E19: unidades/s | G19: Lo rápido que gira el volante virtual | H19: Giro más nervioso | I19: Más suave
A20: MotorCoche | B20: Motor | C20: Fuerza Motor | D20: 9000 | E20: N | F20: 7000 | G20: Empuje total, repartido entre las ruedas de tracción | H20: Acelera más | I20: Acelera menos
A21: MotorCoche | B21: Motor | C21: Fuerza Freno | D21: 8000 | E21: N | F21: 6000 | G21: Fuerza al pedir lo contrario a lo que haces (vas adelante y pulsas S) | H21: Frena más en seco | I21: Frena más suave
A22: MotorCoche | B22: Motor | C22: Velocidad Maxima | D22: 25 | E22: m/s | F22: 30 | G22: Velocidad a la que el motor deja de empujar (25 m/s = 90 km/h) | H22: Más velocidad punta | I22: Menos velocidad punta
A23: MotorCoche | B23: Motor | C23: Rozamiento | D23: 100 | E23: N por m/s | G23: Resistencia constante, también acelerando | H23: Baja la velocidad máxima real | I23: Menos resistencia
A24: MotorCoche | B24: Motor | C24: Freno Motor | D24: 1500 | E24: N por m/s | G24: Resistencia extra solo al soltar el acelerador | H24: Se detiene antes | I24: Rueda más
A25: MotorCoche | B25: Dirección | C25: Angulo Maximo | D25: 30 | E25: grados | F25: 20 | G25: Giro máximo de las ruedas delanteras | H25: Gira más cerrado | I25: Gira más abierto
A26: MotorCoche | B26: Dirección | C26: Giro A Velocidad Maxima | D26: 0.35 | E26: fracción | G26: Porcentaje de giro disponible a tope de velocidad (0.35 = 35 %) | H26: Más sensible a alta velocidad | I26: Más estable a alta velocidad
A27: MotorCoche | B27: Turbo | C27: Multiplicador Turbo | D27: 1.8 | E27: x | G27: Multiplica la fuerza del motor con turbo | H27: Empuje mayor | I27: Empuje menor
A28: MotorCoche | B28: Turbo | C28: Velocidad Maxima Turbo | D28: 32 | E28: m/s | G28: Nuevo techo de velocidad con turbo | H28: Más velocidad punta con turbo | I28: Menos velocidad punta con turbo
A29: MotorCoche | B29: Turbo | C29: Capacidad Turbo | D29: 100 | E29: unidades | G29: Tamaño del depósito de turbo | H29: Dura más | I29: Dura menos
A30: MotorCoche | B30: Turbo | C30: Consumo Turbo | D30: 25 | E30: unidades/s | G30: Lo que gasta por segundo con el turbo activo | H30: Dura menos | I30: Dura más
A31: MotorCoche | B31: Turbo | C31: Recarga Turbo | D31: 10 | E31: unidades/s | G31: Lo que recupera por segundo si no lo usas | H31: Recarga antes | I31: Recarga más lento
A32: AgarreCoche | B32: Agarre lateral | C32: Rigidez Lateral | D32: 4000 | E32: N por m/s | F32: 6000 | G32: Lo fuerte que frena el deslizamiento lateral | H32: Más agarre (si vibra al ir recto, bájala a 2000-3000) | I32: Más deslizamiento
A33: AgarreCoche | B33: Agarre lateral | C33: Coeficiente Agarre | D33: 1 | F33: 2 | G33: Límite de adherencia: fuerza lateral máxima = peso sobre la rueda × este valor. 1 = asfalto, 0.5 = arena suelta | H33: Más agarre | I33: Derrapa antes
A34: AgarreCoche | B34: Freno de mano | C34: Agarre Trasero Con Freno | D34: 0.35 | E34: fracción (0-1) | G34: Fracción de agarre que conservan las traseras con el freno de mano | H34: Menos derrape | I34: Derrapa más fácil
A35: AgarreCoche | B35: Freno de mano | C35: Frenado Freno Mano | D35: 3000 | E35: N por m/s | G35: Cuánto frena hacia delante el freno de mano | H35: Frena más | I35: Frena menos
A36: EstabilidadCoche | B36: Centro de masa | C36: Centro De Masa | D36: (0, -0.4, 0) | E36: m (local) | G36: Punto de equilibrio del coche, relativo a Patrol | H36: Más alto (Y mayor): vuelca fácil | I36: Más bajo (Y negativa): cuesta más volcar
A37: EstabilidadCoche | B37: Damping rotacional | C37: Damping Yaw | D37: 1.5 | F37: 3 | G37: Freno al giro izquierda/derecha del coche | H37: Deja de rotar antes, pero cuesta girar | I37: Gira más libre
A38: EstabilidadCoche | B38: Damping rotacional | C38: Damping Roll | D38: 4 | G38: Freno al vuelco lateral | H38: Se inclina menos | I38: Se inclina más
A39: EstabilidadCoche | B39: Damping rotacional | C39: Damping Pitch | D39: 4 | G39: Freno al cabeceo (morro arriba/abajo) | H39: Cabecea menos | I39: Cabecea más
A40: EstabilidadCoche | B40: Asistencia | C40: Ayudas Activas | D40: Sí | G40: Activa o desactiva la asistencia de alineación (opción de accesibilidad del GDD)
A41: EstabilidadCoche | B41: Asistencia | C41: Velocidad Minima Asistencia | D41: 5 | E41: m/s | G41: Por debajo de esta velocidad la asistencia no actúa | H41: Actúa solo a más velocidad | I41: Actúa también a poca velocidad
A42: EstabilidadCoche | B42: Asistencia | C42: Fuerza Alineacion | D42: 0.05 | G42: Intensidad con la que se alinea el morro con la trayectoria | H42: 'Sobre raíles' | I42: Más libre para derrapar
A43: EstabilidadCoche | B43: Asistencia | C43: Angulo Maximo Asistencia | D43: 45 | E43: grados | G43: Ángulo de derrape a partir del cual la asistencia deja de crecer
A44: CamaraSprung | B44: Objetivo | C44: Objetivo | D44: Patrol | G44: Transform al que sigue la cámara
A45: CamaraSprung | B45: Posición | C45: Distancia Min | D45: 40 | E45: m | G45: Distancia en línea recta al coche, parado | H45: Coche más pequeño en pantalla | I45: Coche más grande
A46: CamaraSprung | B46: Posición | C46: Distancia Max | D46: 46 | E46: m | G46: Distancia en línea recta a tope de velocidad (se aleja al ir rápido) | H46: Más sensación de velocidad | I46: Menos
A47: CamaraSprung | B47: Posición | C47: Angulo Elevacion | D47: 78 | E47: grados | G47: Cuánto mira hacia abajo: 0 = a la altura del coche, 90 = cenital puro (no pasar de 85) | H47: Más vista de pájaro | I47: Más horizonte
A48: CamaraSprung | B48: Posición | C48: Adelanto Min | D48: 5 | E48: m | G48: El centro del encuadre va por delante del coche (parado). Más adelanto = coche más abajo en pantalla | H48: Coche más abajo, ves más camino | I48: Coche más centrado
A49: CamaraSprung | B49: Posición | C49: Adelanto Max | D49: 8 | E49: m | G49: Igual que Adelanto Min pero a tope de velocidad | H49: Ves más camino a gran velocidad | I49: Menos
A50: CamaraSprung | B50: Resorte | C50: Rigidez | D50: 20 | G50: Fuerza del resorte que tira de la cámara hacia su posición deseada | H50: Cámara pegada al coche | I50: Más retraso, más suave
A51: CamaraSprung | B51: Resorte | C51: Factor Amortiguacion | D51: 0.9 | E51: 0.2-1.5 | G51: 1 = sin rebote (amortiguación crítica), menor de 1 = rebota | H51: Sin rebote, más lenta | I51: Rebota más
A52: CamaraSprung | B52: Dirección (drift) | C52: Seguir Trayectoria | D52: 1 | E52: 0-1 | G52: 0 = la cámara gira con el morro, 1 = sigue la dirección de la velocidad | H52: Derrape más visible de lado | I52: Cámara gira con el coche
A53: CamaraSprung | B53: Dirección (drift) | C53: Velocidad Minima Trayectoria | D53: 4 | E53: m/s | G53: Por debajo de esta velocidad la cámara usa el morro del coche | H53: Usa el morro hasta más velocidad | I53: Sigue la trayectoria antes
A54: CamaraSprung | B54: Dirección (drift) | C54: Suavizado Giro | D54: 2.5 | G54: Lo rápido que la cámara gira hacia su dirección deseada | H54: Gira casi con el coche | I54: Gira con más retraso (el derrape se nota más)
A55: CamaraSprung | B55: Velocidad | C55: Velocidad Referencia | D55: 25 | E55: m/s | G55: Velocidad a la que se llega al máximo de distancia, adelanto y FOV | H55: Tarda más en abrirse | I55: Se abre antes
A56: CamaraSprung | B56: FOV | C56: Fov Base | D56: 35 | E56: grados | G56: Campo de visión parado (bajo = imagen más plana, estilo móvil) | H56: Más gran angular | I56: Más plano
A57: CamaraSprung | B57: FOV | C57: Fov Maximo | D57: 40 | E57: grados | G57: Campo de visión a tope de velocidad | H57: Más efecto de velocidad | I57: Menos
A58: CamaraSprung | B58: FOV | C58: Fov Extra Turbo | D58: 5 | E58: grados | G58: FOV extra mientras el turbo está activo | H58: Turbo se nota más | I58: Menos
A59: CamaraSprung | B59: FOV | C59: Suavizado Fov | D59: 4 | G59: Lo rápido que el FOV persigue su valor deseado | H59: Cambia más rápido | I59: Más suave
A60: MaterialChatarra (asset) | B60: Datos | C60: Nombre | D60: Metal / Cobre / Goma | G60: Nombre que se muestra en el inventario y la tienda. Si queda vacío usa el nombre del archivo
A61: MaterialChatarra (asset) | B61: Datos | C61: Color | D61: gris / naranja / negro | G61: Color del cubo de la pieza y de la casilla del inventario
A62: MaterialChatarra (asset) | B62: Datos | C62: Icono | D62: (opcional) | G62: Sprite que se dibuja en la casilla del inventario. Texture Type debe ser Sprite (2D and UI)
A63: MaterialChatarra (asset) | B63: Datos | C63: Valor Base | D63: 10 | E63: monedas | G63: Precio de referencia en la tienda (Metal 10, Cobre 25, Goma 5) | H63: Más dinero por pieza | I63: Menos
A64: MaterialChatarra (asset) | B64: Datos | C64: Espacio | D64: 1 | E64: unidades de maletero | G64: Cuánto ocupa cada unidad en el maletero (Goma 2) | H64: Llena el maletero antes | I64: Cabe más
A65: Destruible | B65: Rotura | C65: Velocidad Minima | D65: 8 | E65: m/s | G65: Velocidad de impacto para romperlo (8 m/s ≈ 29 km/h) | H65: Hay que ir más rápido | I65: Se rompe con roces
A66: Destruible | B66: Fragmentos | C66: Prefab Fragmento | D66: Fragmento | G66: Cubo decorativo que sale al romperse (Rigidbody, capa Fragmentos)
A67: Destruible | B67: Fragmentos | C67: Cantidad Fragmentos | D67: 10 | E67: unidades | G67: Cuántos cubitos decorativos salen | H67: Más espectáculo, más coste | I67: Menos
A68: Destruible | B68: Fragmentos | C68: Color Fragmentos | D68: gris | G68: Color de los cubitos decorativos
A69: Destruible | B69: Fragmentos | C69: Vida Fragmentos | D69: 4 | E69: s | G69: Segundos hasta que desaparecen los fragmentos | H69: Más desorden | I69: Se limpian antes
A70: Destruible | B70: Fragmentos | C70: Fuerza Fragmentos | D70: 6 | E70: m/s | G70: Velocidad con la que salen disparados | H70: Salen más lejos | I70: Salen poco
A71: Destruible | B71: Botín | C71: Prefab Recolectable | D71: Pieza | G71: Prefab de la pieza recogible (debe tener el script Recolectable, capa Recolectable)
A72: Destruible | B72: Botín | C72: Botin (lista) | D72: p. ej. Metal 1-3, Cobre 0-2 | G72: Lista de qué suelta: Tipo (material), Mínimo y Máximo. Cantidad aleatoria entre ambos | H72: Más botín | I72: Menos
A73: Recolectable | B73: Pieza | C73: Tipo | D73: (lo pone Destruible) | G73: Material de la pieza
A74: Recolectable | B74: Pieza | C74: Cantidad | D74: 1 | E74: unidades | G74: Unidades que da la pieza al recogerla | H74: Más por pieza | I74: Menos
A75: Recolectable | B75: Pieza | C75: Retraso Recogida | D75: 1 | E75: s | G75: Segundos tras aparecer en los que no se puede recoger (evita sumar al chocar) | H75: Hay que volver a por ellas | I75: Se recogen casi al instante
A76: RecolectorCoche | B76: Zona de recogida | C76: Centro | D76: (0, -0.5, 0) | E76: m (local) | G76: Centro de la esfera de recogida, relativo a Patrol. Debe quedar a la altura del suelo
A77: RecolectorCoche | B77: Zona de recogida | C77: Radio | D77: 2.5 | E77: m | G77: Radio de la esfera de recogida | H77: Recoge de más lejos | I77: Hay que pasar justo por encima
A78: RecolectorCoche | B78: Zona de recogida | C78: Capa Recolectable | D78: Recolectable | G78: Capa que busca la esfera. Solo ve esa capa
A79: InventarioCoche | B79: Maletero | C79: Capacidad | D79: 20 | E79: unidades de maletero | G79: Espacio total del maletero (la mejora Maletero del garaje la subirá) | H79: Cabe más botín | I79: Se llena antes
A80: InventarioUI | B80: Origen | C80: Inventario | D80: Patrol | G80: InventarioCoche que se muestra
A81: InventarioUI | B81: Posición y tamaño | C81: Margen | D81: (30, 30) | E81: px | G81: Distancia a la esquina superior izquierda
A82: InventarioUI | B82: Posición y tamaño | C82: Ancho Barra | D82: 360 | E82: px | G82: Ancho de la barra de capacidad y de la fila de casillas | H82: HUD más grande | I82: Más pequeño
A83: InventarioUI | B83: Posición y tamaño | C83: Alto Barra | D83: 28 | E83: px | G83: Alto de la barra de capacidad
A84: InventarioUI | B84: Posición y tamaño | C84: Tamano Casilla | D84: 76 | E84: px | G84: Lado de cada casilla de material
A85: InventarioUI | B85: Posición y tamaño | C85: Separacion | D85: 8 | E85: px | G85: Hueco entre casillas
A86: InventarioUI | B86: Colores | C86: Color Fondo | D86: negro 55 % | G86: Fondo de barra y casillas
A87: InventarioUI | B87: Colores | C87: Color Barra | D87: verde | G87: Color del relleno de la barra de capacidad
A88: InventarioUI | B88: Colores | C88: Color Barra Llena | D88: rojo | G88: Color de la barra cuando el maletero está lleno
A89: InventarioUI | B89: Texto | C89: Tamano Texto | D89: 22 | E89: px | G89: Tamaño base del texto del HUD
A90: InventarioUI | B90: Pulso al recoger | C90: Fuerza Pulso | D90: 0.3 | E90: fracción | G90: Cuánto crece la casilla al recoger (0.3 = 30 %) | H90: Pulso más marcado | I90: Más sutil
A91: InventarioUI | B91: Pulso al recoger | C91: Velocidad Pulso | D91: 4 | G91: Lo rápido que la casilla vuelve a su tamaño | H91: Vuelve antes | I91: El pulso dura más
A92: GasolinaCoche | B92: Depósito | C92: Capacidad | D92: 100 | E92: unidades | G92: Tamaño del depósito (la mejora de gasolina podrá subirlo). Para probar, pon 15 | H92: Más autonomía | I92: Menos autonomía
A93: GasolinaCoche | B93: Depósito | C93: Umbral Reserva | D93: 0.2 | E93: fracción (0-1) | G93: Por debajo de este nivel la barra parpadea (aviso de reserva) | H93: Avisa antes | I93: Avisa más tarde
A94: GasolinaCoche | B94: Consumo | C94: Consumo Ralenti | D94: 0.1 | E94: unidades/s | G94: Gasto constante, aunque estés parado | H94: Presión constante, no puedes quedarte quieto | I94: 0 = parado no gasta
A95: GasolinaCoche | B95: Consumo | C95: Consumo Acelerando | D95: 0.5 | E95: unidades/s | G95: Gasto extra a acelerador a fondo (se escala con el acelerador) | H95: Conducir a fondo cuesta más | I95: Menos
A96: GasolinaCoche | B96: Consumo | C96: Consumo Turbo | D96: 2 | E96: unidades/s | G96: Gasto extra mientras el turbo está activo (el castigo del GDD) | H96: El turbo cuesta más | I96: Menos
A97: GasolinaCoche | B97: Colisiones | C97: Impacto Minimo | D97: 6 | E97: m/s | G97: Por debajo de esta velocidad de impacto el choque no cuesta gasolina | H97: Roces gratis | I97: Cualquier roce cuesta
A98: GasolinaCoche | B98: Colisiones | C98: Perdida Por Impacto | D98: 0.8 | E98: unidades por m/s | G98: Gasolina perdida por cada m/s de impacto por encima del mínimo | H98: Choques más caros | I98: Choques más baratos
A99: GasolinaCoche | B99: Colisiones | C99: Factor Carroceria | D99: 1 | E99: x | G99: Multiplicador de la pérdida por choque. La mejora Carrocería lo bajará (0.5 = la mitad) | H99: Choques más caros | I99: Choques más baratos
A100: GasolinaUI | B100: Origen | C100: Gasolina | D100: Patrol | G100: GasolinaCoche que se muestra
A101: GasolinaUI | B101: Origen | C101: Motor | D101: Patrol | G101: MotorCoche, para dibujar la barra de turbo
...

Sheet Relaciones
A1: Relaciones útiles (se recalculan con 'Mi valor' o, si está vacío, con el valor inicial)
A3: Datos de entrada (leídos de la hoja Variables)
A4: Dato | B4: Valor | C4: Unidad | D4: Origen
A5: Masa del coche | B5: =IF(Variables!F110="",Variables!D110,Variables!F110) -> 1500 | C5: kg | D5: Hoja Variables: Rigidbody (Patrol) › Mass
A6: Rigidez del resorte | B6: =IF(Variables!F13="",Variables!D13,Variables!F13) -> 25000 | C6: N/m | D6: Hoja Variables: SuspensionCoche › Rigidez
A7: Longitud máxima del resorte | B7: =IF(Variables!F11="",Variables!D11,Variables!F11) -> 0.9 | C7: m | D7: Hoja Variables: SuspensionCoche › Longitud Maxima
A8: Radio de la rueda | B8: =IF(Variables!F12="",Variables!D12,Variables!F12) -> 0.5 | C8: m | D8: Hoja Variables: SuspensionCoche › Radio Rueda
A9: Velocidad máxima | B9: =IF(Variables!F22="",Variables!D22,Variables!F22) -> 30 | C9: m/s | D9: Hoja Variables: MotorCoche › Velocidad Maxima
A10: Capacidad del turbo | B10: =IF(Variables!F29="",Variables!D29,Variables!F29) -> 100 | C10: unidades | D10: Hoja Variables: MotorCoche › Capacidad Turbo
A11: Consumo del turbo (depósito) | B11: =IF(Variables!F30="",Variables!D30,Variables!F30) -> 25 | C11: unidades/s | D11: Hoja Variables: MotorCoche › Consumo Turbo
A12: Recarga del turbo | B12: =IF(Variables!F31="",Variables!D31,Variables!F31) -> 10 | C12: unidades/s | D12: Hoja Variables: MotorCoche › Recarga Turbo
A13: Capacidad de gasolina | B13: =IF(Variables!F92="",Variables!D92,Variables!F92) -> 100 | C13: unidades | D13: Hoja Variables: GasolinaCoche › Capacidad
A14: Consumo ralentí | B14: =IF(Variables!F94="",Variables!D94,Variables!F94) -> 0.1 | C14: unidades/s | D14: Hoja Variables: GasolinaCoche › Consumo Ralenti
A15: Consumo acelerando | B15: =IF(Variables!F95="",Variables!D95,Variables!F95) -> 0.5 | C15: unidades/s | D15: Hoja Variables: GasolinaCoche › Consumo Acelerando
A16: Consumo turbo (gasolina) | B16: =IF(Variables!F96="",Variables!D96,Variables!F96) -> 2 | C16: unidades/s | D16: Hoja Variables: GasolinaCoche › Consumo Turbo
A17: Impacto mínimo que cuesta gasolina | B17: =IF(Variables!F97="",Variables!D97,Variables!F97) -> 6 | C17: m/s | D17: Hoja Variables: GasolinaCoche › Impacto Minimo
A18: Pérdida por impacto | B18: =IF(Variables!F98="",Variables!D98,Variables!F98) -> 0.8 | C18: unidades por m/s | D18: Hoja Variables: GasolinaCoche › Perdida Por Impacto
A19: Factor carrocería | B19: =IF(Variables!F99="",Variables!D99,Variables!F99) -> 1 | C19: x | D19: Hoja Variables: GasolinaCoche › Factor Carroceria
A20: Velocidad mínima de rotura (Destruible) | B20: =IF(Variables!F65="",Variables!D65,Variables!F65) -> 8 | C20: m/s | D20: Hoja Variables: Destruible › Velocidad Minima
A21: Capacidad del maletero | B21: =IF(Variables!F79="",Variables!D79,Variables!F79) -> 20 | C21: unidades | D21: Hoja Variables: InventarioCoche › Capacidad
A22: Distancia de cámara (parado) | B22: =IF(Variables!F45="",Variables!D45,Variables!F45) -> 40 | C22: m | D22: Hoja Variables: CamaraSprung › Distancia Min
A23: Ángulo de elevación de la cámara | B23: =IF(Variables!F47="",Variables!D47,Variables!F47) -> 78 | C23: grados | D23: Hoja Variables: CamaraSprung › Angulo Elevacion
A24: Adelanto de cámara (parado) | B24: =IF(Variables!F48="",Variables!D48,Variables!F48) -> 5 | C24: m | D24: Hoja Variables: CamaraSprung › Adelanto Min
A25: Gravedad | B25: 9.81 | C25: m/s² | D25: Constante física (valor estándar)
A26: Número de ruedas | B26: 4 | C26: ud | D26: Coche de 4 ruedas (supuesto: reparto de peso uniforme)
A27: Velocidad de impacto a probar | B27: 12 | C27: m/s | D27: EDITABLE: ejemplo de choque (12 m/s ≈ 43 km/h) para calcular su coste en gasolina
A29: Suspensión
A30: Resultado | B30: Valor | C30: Unidad | D30: Cómo se calcula
A31: Peso por rueda | B31: =B5*B25/B26 -> 3678.75 | C31: N | D31: masa × gravedad / nº de ruedas
A32: Compresión del resorte en reposo | B32: =B31/B6 -> 0.14715 | C32: m | D32: peso por rueda / rigidez
A33: Alcance máximo del SphereCast | B33: =B8+B7 -> 1.4 | C33: m | D33: radio + longitud máxima (el anclaje debe estar por debajo de esto para tocar suelo)
A34: Altura del anclaje en reposo | B34: =B8+B7-B32 -> 1.25285 | C34: m | D34: radio + longitud máxima − compresión en reposo
A35: Compresión en reposo (% del recorrido) | B35: =B32/B7 -> 0.1635 | C35: % | D35: compresión / longitud máxima
A37: Motor y turbo
A38: Resultado | B38: Valor | C38: Unidad | D38: Cómo se calcula
A39: Velocidad máxima | B39: =B9*3.6 -> 108 | C39: km/h | D39: m/s × 3.6
A40: Duración del depósito de turbo | B40: =B10/B11 -> 4 | C40: s | D40: capacidad / consumo
A41: Recarga completa del depósito de turbo | B41: =B10/B12 -> 10 | C41: s | D41: capacidad / recarga
A43: Gasolina (¿hasta cuándo puedes explorar?)
A44: Resultado | B44: Valor | C44: Unidad | D44: Cómo se calcula
A45: Autonomía solo en ralentí (parado) | B45: =IF(B14>0,B13/B14,"sin límite") -> 1000 | C45: s | D45: capacidad / consumo en ralentí
A46: Autonomía a fondo (ralentí + acelerando) | B46: =B13/(B14+B15) -> 166.66667 | C46: s | D46: capacidad / (ralentí + acelerando)
A47: Autonomía a fondo (en minutos) | B47: =B46/60 -> 2.7777778 | C47: min | D47: segundos / 60
A48: Autonomía a fondo con turbo siempre activo | B48: =B13/(B14+B15+B16) -> 38.461538 | C48: s | D48: capacidad / (ralentí + acelerando + turbo). Solo teórico: el depósito de turbo se acaba antes
A49: Distancia recorrida con el depósito a fondo | B49: =B46*B9/1000 -> 5 | C49: km | D49: autonomía a fondo × velocidad máxima (cota superior: no se va siempre a tope)
A50: Gasolina que cuesta el choque de prueba | B50: =MAX(0,B27-B17)*B18*B19 -> 4.8 | C50: unidades | D50: (velocidad − impacto mínimo) × pérdida por impacto × factor carrocería
A51: …como % del depósito | B51: =B50/B13 -> 0.048 | C51: % | D51: coste del choque / capacidad
A53: Romper y recoger
A54: Resultado | B54: Valor | C54: Unidad | D54: Cómo se calcula
A55: Velocidad mínima de rotura | B55: =B20*3.6 -> 28.8 | C55: km/h | D55: m/s × 3.6
A56: Piezas de 1 unidad que caben en el maletero | B56: =B21 -> 20 | C56: ud | D56: capacidad (cada unidad de Metal o Cobre ocupa 1; la Goma ocupa 2)
A58: Cámara
A59: Resultado | B59: Valor | C59: Unidad | D59: Cómo se calcula
A60: Altura de la cámara sobre el coche (parado) | B60: =B22*SIN(RADIANS(B23)) -> 39.125904 | C60: m | D60: distancia × sen(ángulo)
A61: Distancia horizontal detrás del centro del encuadre | B61: =B22*COS(RADIANS(B23)) -> 8.3164676 | C61: m | D61: distancia × cos(ángulo)
A62: Distancia horizontal detrás del coche | B62: =B61-B24 -> 3.3164676 | C62: m | D62: horizontal − adelanto (si es negativa, la cámara queda por delante del coche)
A64: Reglas rápidas
A65: • Rigidez y Amortiguación van juntas: si cambias una, revisa la otra.
A66: • Radio Rueda debe ser siempre el del neumático visual. Si cambias de modelo, mídelo de nuevo.
A67: • Si la compresión en reposo supera ~50 % del recorrido, el cuerpo tocará fondo con facilidad: sube Rigidez o Longitud Máxima.
A68: • Coeficiente Agarre y Rigidez Lateral controlan el derrape juntos: el primero marca dónde se pierde el agarre, el segundo lo fuerte que se corrige antes de perderlo.
A69: • Para probar la gasolina rápido, pon Capacidad en 15 y vuelve a 100 al terminar.
A70: • Los destruibles deben medir ~1.5 m de alto: el coche no tiene colliders en las ruedas y la carrocería está elevada.
